{
  "schemaId": "delegate",
  "version": "1.0.1",
  "cid": "QmcHmNS3NhcrMgXmCm72bv77EKUx7inoeaS2QeWDuQGU1q",
  "checksum": "sha256:4208b2eec2ddf8d4ded2df34999070a21779af793d3b09b95f0a5cede999adf7",
  "timestamp": 1771433406,
  "schemaPath": "packages/schemas/published/delegate/versions/1.0.1/schema.json",
  "publisher": "pinata",
  "signer": "0x6837047F46Da1d5d9A79846b25810b92adF456F6",
  "signature": "0x64f92e40ec389534f2fc16c8502994587cbfcec97308fe2cbbcc3323cc24f71a7161f39aa61668a713e3e1385567d30c965aa484424cd9a3d054a515cebeef211b",
  "eip712": {
    "domain": {
      "name": "ENS Schema Publisher",
      "version": "1"
    },
    "types": {
      "PublishedSchema": [
        {
          "name": "schemaId",
          "type": "string"
        },
        {
          "name": "version",
          "type": "string"
        },
        {
          "name": "cid",
          "type": "string"
        },
        {
          "name": "checksum",
          "type": "string"
        },
        {
          "name": "timestamp",
          "type": "uint256"
        },
        {
          "name": "schemaPath",
          "type": "string"
        },
        {
          "name": "publisher",
          "type": "string"
        },
        {
          "name": "notes",
          "type": "string"
        }
      ]
    },
    "primaryType": "PublishedSchema",
    "message": {
      "schemaId": "delegate",
      "version": "1.0.1",
      "cid": "QmcHmNS3NhcrMgXmCm72bv77EKUx7inoeaS2QeWDuQGU1q",
      "checksum": "sha256:4208b2eec2ddf8d4ded2df34999070a21779af793d3b09b95f0a5cede999adf7",
      "timestamp": 1771433406,
      "schemaPath": "packages/schemas/published/delegate/versions/1.0.1/schema.json",
      "publisher": "pinata",
      "notes": ""
    }
  }
}
